creature/__init__.py
creature/_loop.py
creature/as_async.py
creature/context_managers.py
creature/context_vars.py
creature/exempt.py
creature/ipy/__init__.py
creature/ipy/descriptor.py
creature/ipy/runner.py
creature/iterators.py
creature/start_loop.py
creature/utils.py
creature-0.1.17.dist-info/LICENSE
creature-0.1.17.dist-info/METADATA
creature-0.1.17.dist-info/WHEEL
creature-0.1.17.dist-info/RECORD
