Metadata-Version: 2.1
Name: creature
Version: 0.1.17
Summary: 
Keywords: greenlet,fibers,async,sqlalchemy
Author: pwtail
Author-email: abvit89s@gmail.com
Requires-Python: >=3.10,<4.0
Classifier: Programming Language :: Python :: 3
Classifier: Programming Language :: Python :: 3.10
Classifier: Programming Language :: Python :: 3.11
Requires-Dist: greenlet (>=2.0.1,<3.0.0)
